Witmotion16chServoDriverV2/Witmotion16chServoDriverV2.py
Witmotion16chServoDriverV2/__init__.py
Witmotion16chServoDriverV2-0.1.0.dist-info/LICENSE
Witmotion16chServoDriverV2-0.1.0.dist-info/METADATA
Witmotion16chServoDriverV2-0.1.0.dist-info/WHEEL
Witmotion16chServoDriverV2-0.1.0.dist-info/top_level.txt
Witmotion16chServoDriverV2-0.1.0.dist-info/RECORD
