Metadata-Version: 2.1
Name: Witmotion16chServoDriverV2
Version: 0.1.0
Summary: A driver for comminucating with Witmotion 16 channel servo microcontroller over Bluetooth + Serial
Author: Lidor Shimoni
Author-email: lidor.shim@gmail.com
Classifier: Programming Language :: Python :: 3
Classifier: License :: OSI Approved :: MIT License
Classifier: Operating System :: OS Independent
Requires-Python: >=3.6
License-File: LICENSE
